LICENSE
MANIFEST.in
README.rst
requirements.txt
setup.cfg
setup.py
spotcot/__init__.py
spotcot/classes.py
spotcot/commands.py
spotcot/constants.py
spotcot/functions.py
spotcot.egg-info/PKG-INFO
spotcot.egg-info/SOURCES.txt
spotcot.egg-info/dependency_links.txt
spotcot.egg-info/entry_points.txt
spotcot.egg-info/not-zip-safe
spotcot.egg-info/requires.txt
spotcot.egg-info/top_level.txt