Metadata-Version: 1.1
Name: spotcot
Version: 2.0.2
Summary: Spot Cursor-on-Target Gateway.
Home-page: https://github.com/ampledata/spotcot
Author: Greg Albrecht
Author-email: oss@undef.net
License: Copyright 2020 Orion Labs, Inc.
